{
  "main": {
    "id": "e3767cfc31b884ee",
    "type": "split",
    "children": [
      {
        "id": "7d249c077c553734",
        "type": "tabs",
        "children": [
          {
            "id": "ab038db392d9e38e",
            "type": "leaf",
            "state": {
              "type": "markdown",
              "state": {
                "file": "Notes/Subnet.md",
                "mode": "source",
                "source": false
              }
            }
          }
        ]
      }
    ],
    "direction": "vertical"
  },
  "left": {
    "id": "2f68880252f1fc9a",
    "type": "split",
    "children": [
      {
        "id": "4b875c666e1f0f4a",
        "type": "tabs",
        "children": [
          {
            "id": "7d4e4f6c2b126dad",
            "type": "leaf",
            "state": {
              "type": "file-explorer",
              "state": {
                "sortOrder": "alphabetical"
              }
            }
          },
          {
            "id": "77f1d094f0d175a5",
            "type": "leaf",
            "state": {
              "type": "search",
              "state": {
                "query": "",
                "matchingCase": false,
                "explainSearch": false,
                "collapseAll": false,
                "extraContext": false,
                "sortOrder": "alphabetical"
              }
            }
          },
          {
            "id": "cd6afee39fba7de5",
            "type": "leaf",
            "state": {
              "type": "bookmarks",
              "state": {}
            }
          }
        ]
      }
    ],
    "direction": "horizontal",
    "width": 300
  },
  "right": {
    "id": "500fb7a18f505b65",
    "type": "split",
    "children": [
      {
        "id": "32e6e9d9601951f7",
        "type": "tabs",
        "children": [
          {
            "id": "5cd5a921127afb3e",
            "type": "leaf",
            "state": {
              "type": "backlink",
              "state": {
                "file": "Notes/Subnet.md",
                "collapseAll": false,
                "extraContext": false,
                "sortOrder": "alphabetical",
                "showSearch": false,
                "searchQuery": "",
                "backlinkCollapsed": false,
                "unlinkedCollapsed": true
              }
            }
          },
          {
            "id": "a8f6c415029ca15e",
            "type": "leaf",
            "state": {
              "type": "outgoing-link",
              "state": {
                "file": "Notes/Subnet.md",
                "linksCollapsed": false,
                "unlinkedCollapsed": true
              }
            }
          },
          {
            "id": "48c7492f9c6232bc",
            "type": "leaf",
            "state": {
              "type": "tag",
              "state": {
                "sortOrder": "frequency",
                "useHierarchy": true
              }
            }
          },
          {
            "id": "707d4bef2f0bf8de",
            "type": "leaf",
            "state": {
              "type": "outline",
              "state": {
                "file": "Notes/Subnet.md"
              }
            }
          }
        ]
      }
    ],
    "direction": "horizontal",
    "width": 300,
    "collapsed": true
  },
  "left-ribbon": {
    "hiddenItems": {
      "switcher:Open quick switcher": false,
      "graph:Open graph view": false,
      "canvas:Create new canvas": false,
      "daily-notes:Open today's daily note": false,
      "templates:Insert template": false,
      "command-palette:Open command palette": false
    }
  },
  "active": "ab038db392d9e38e",
  "lastOpenFiles": [
    "Configure/Router configurations.md",
    "Notes/Subnet.md",
    "Notes/DevNet Associate.md"
  ]
}